wellcompare/__init__.py
wellcompare/__main__.py
wellcompare/app.py
wellcompare/combine.py
wellcompare/extract.py
wellcompare/graph.py
wellcompare/graph_repl.py
wellcompare/grph.py
wellcompare/heatmap.py
wellcompare/plate.py
wellcompare/process.py
wellcompare/graph/__init__.py
wellcompare/graph/app.py
wellcompare/graph/helpers/__init__.py
wellcompare/graph/helpers/combine.py
wellcompare/graph/helpers/extract.py
wellcompare/helpers/__init__.py
wellcompare/helpers/combine.py
wellcompare/helpers/extract.py
wellcompare_old_code/__init__.py
wellcompare_old_code/__main__.py
wellcompare_old_code/combine.py
wellcompare_old_code/extract.py
wellcompare_old_code/graph_repl.py
wellcompare_old_code/grph.py
wellcompare_old_code/heatmap.py
wellcompare_old_code/process.py
wellcompare-2.3.4.dist-info/LICENSE
wellcompare-2.3.4.dist-info/METADATA
wellcompare-2.3.4.dist-info/WHEEL
wellcompare-2.3.4.dist-info/top_level.txt
wellcompare-2.3.4.dist-info/RECORD
