Metadata-Version: 2.1
Name: wellcompare
Version: 2.3.4
Summary: A package for doing a well to well analysis of 96 well plates run in an Epoch2 microplate reader
Home-page: https://github.com/jacobian0208/well_compare_96
Author: Jacob Evarts
Author-email: jevarts@uoregon.edu
License: UNKNOWN
Project-URL: Bug Reports, https://github.com/jacobian0208/well_compare_96/issus
Platform: UNKNOWN
Classifier: Development Status :: 3 - Alpha
Classifier: Natural Language :: English
Classifier: Intended Audience :: Science/Research
Classifier: Programming Language :: Python :: 3
Classifier: License :: OSI Approved :: MIT License
Classifier: Operating System :: OS Independent
Requires-Python: >=3.6
Requires-Dist: numpy
Requires-Dist: pandas
Requires-Dist: scipy
Requires-Dist: seaborn
Requires-Dist: matplotlib
Requires-Dist: argparse
Requires-Dist: openpyxl
Requires-Dist: xlrd (>=1.0.0)
